{"category":"Health_and_Personal_Care","month":5,"year":2010,"count":685,"sale":14659.310105755925}
{"category":"Health_and_Personal_Care","month":5,"year":2009,"count":259,"sale":7240.950013170019}
{"category":"Health_and_Personal_Care","month":5,"year":2008,"count":203,"sale":5410.270033121109}
{"category":"Health_and_Personal_Care","month":5,"year":2007,"count":76,"sale":1715.1600184440613}
{"category":"Health_and_Personal_Care","month":5,"year":2006,"count":12,"sale":442.1700077056885}
{"category":"Health_and_Personal_Care","month":5,"year":2005,"count":4,"sale":251.60000610351562}
{"category":"Health_and_Personal_Care","month":5,"year":2004,"count":4,"sale":59.10000133514404}
{"category":"Health_and_Personal_Care","month":4,"year":2014,"count":10077,"sale":201464.57035345025}
{"category":"Health_and_Personal_Care","month":4,"year":2013,"count":9196,"sale":183517.77013452724}
{"category":"Health_and_Personal_Care","month":4,"year":2012,"count":2169,"sale":48175.1800285317}
{"category":"Health_and_Personal_Care","month":4,"year":2011,"count":1258,"sale":29944.66007436067}
