{"category":"Toys_and_Games","month":6,"year":2005,"count":33,"avg_rating":4.151515151515151}
{"category":"Toys_and_Games","month":6,"year":2004,"count":8,"avg_rating":4.875}
{"category":"Toys_and_Games","month":6,"year":2003,"count":21,"avg_rating":4.761904761904762}
{"category":"Toys_and_Games","month":5,"year":2014,"count":3037,"avg_rating":4.40006585446164}
{"category":"Toys_and_Games","month":5,"year":2013,"count":2462,"avg_rating":4.419171405361495}
{"category":"Toys_and_Games","month":5,"year":2012,"count":1105,"avg_rating":4.294117647058823}
{"category":"Toys_and_Games","month":5,"year":2011,"count":589,"avg_rating":4.34804753820034}
{"category":"Toys_and_Games","month":5,"year":2010,"count":212,"avg_rating":4.150943396226415}
{"category":"Toys_and_Games","month":5,"year":2009,"count":133,"avg_rating":4.398496240601504}
{"category":"Toys_and_Games","month":5,"year":2008,"count":81,"avg_rating":4.493827160493828}
{"category":"Toys_and_Games","month":5,"year":2007,"count":52,"avg_rating":4.173076923076923}
{"category":"Toys_and_Games","month":5,"year":2006,"count":25,"avg_rating":4.52}
